beancount_nblock/__init__.py
beancount_nblock/common.py
beancount_nblock/file_ordering.py
beancount_nblock/repel.py
beancount_nblock/unlinked_documents.py
beancount_nblock-0.2.1.dist-info/licenses/LICENSE
beancount_nblock-0.2.1.dist-info/METADATA
beancount_nblock-0.2.1.dist-info/WHEEL
beancount_nblock-0.2.1.dist-info/top_level.txt
beancount_nblock-0.2.1.dist-info/RECORD
