Metadata-Version: 2.4
Name: beancount-nblock
Version: 0.2.1
Summary: A collection of beancount plugins
Author-email: Florian Preinstorfer <site-github@nblock.org>
License-Expression: GPL-2.0-or-later
Project-URL: Repository, https://github.com/nblock/beancount-nblock
Requires-Python: >=3.11
License-File: LICENSE
Requires-Dist: beancount
Provides-Extra: test
Requires-Dist: coverage; extra == "test"
Requires-Dist: pytest; extra == "test"
Requires-Dist: pytest-randomly; extra == "test"
Dynamic: license-file
